[
  {
    "name": "devflow",
    "project_name": "applications",
    "repo_url": "https://github.com/bsonger/devflow.git",
    "active_manifest_name": "",
    "replica": 5,
    "type": "canary",
    "config_maps": [
      {
        "name": "config-volume",
        "mount_path": "/etc/devflow/config",
        "files_path": null
      }
    ],
    "service": {
      "Ports": [
        {
          "name": "http",
          "port": 8080,
          "target_port": 8080
        }
      ]
    },
    "internet": "external",
    "status": ""
  },
  {
    "name": "document",
    "project_name": "applications",
    "repo_url": "https://github.com/bsonger/Document.git",
    "active_manifest_name": "",
    "replica": 1,
    "type": "normal",
    "service": {
      "Ports": [
        {
          "name": "http",
          "port": 8080,
          "target_port": 8080
        }
      ]
    },
    "internet": "external",
    "status": ""
  },
  {
    "name": "devflow-controller",
    "project_name": "common",
    "repo_url": "https://github.com/bsonger/devflow-controller.git",
    "active_manifest_name": "",
    "replica": 1,
    "type": "normal",
    "config_maps": [
      {
        "name": "config-volume",
        "mount_path": "/etc/devflow-controller/config",
        "files_path": {
          "prod": "/app/devflow-controller/config-volume/prod"
        }
      }
    ],
    "service": {
      "Ports": null
    },
    "internet": "internal",
    "status": ""
  },
  {
    "name": "devflow-console",
    "project_name": "applications",
    "repo_url": "https://github.com/bsonger/devflow-console.git",
    "active_manifest_name": "",
    "replica": 3,
    "type": "blue-green",
    "service": {
      "Ports": [
        {
          "name": "http",
          "port": 8080,
          "target_port": 8080
        }
      ]
    },
    "internet": "external",
    "status": ""
  },
  {
    "name": "devflow-plugin",
    "project_name": "applications",
    "repo_url": "https://github.com/bsonger/devflow-plugin.git",
    "active_manifest_name": "",
    "type": "",
    "service": {
      "Ports": null
    },
    "internet": "",
    "status": ""
  }
]
